cellmap_analyze/__init__.py
cellmap_analyze/analyze/__init__.py
cellmap_analyze/analyze/assign_to_cells.py
cellmap_analyze/analyze/fit_lines_to_segmentations.py
cellmap_analyze/analyze/measure.py
cellmap_analyze/cythonizing/__init__.py
cellmap_analyze/cythonizing/bresenham3D.c
cellmap_analyze/cythonizing/bresenham3D.cpython-312-x86_64-linux-gnu.so
cellmap_analyze/cythonizing/bresenham3D.pyx
cellmap_analyze/cythonizing/centers.cpp
cellmap_analyze/cythonizing/centers.cpython-312-x86_64-linux-gnu.so
cellmap_analyze/cythonizing/centers.pyx
cellmap_analyze/cythonizing/process_arrays.c
cellmap_analyze/cythonizing/process_arrays.cpython-312-x86_64-linux-gnu.so
cellmap_analyze/cythonizing/process_arrays.pyx
cellmap_analyze/cythonizing/touching.c
cellmap_analyze/cythonizing/touching.cpython-312-x86_64-linux-gnu.so
cellmap_analyze/cythonizing/touching.pyx
cellmap_analyze/cythonizing/impl/centers.hpp
cellmap_analyze/process/__init__.py
cellmap_analyze/process/clean_connected_components.py
cellmap_analyze/process/connected_components.py
cellmap_analyze/process/contact_sites.py
cellmap_analyze/process/fill_holes.py
cellmap_analyze/process/filter_ids.py
cellmap_analyze/process/label_with_mask.py
cellmap_analyze/process/morphological_operations.py
cellmap_analyze/process/mutex_watershed.py
cellmap_analyze/process/skeletonize.py
cellmap_analyze/process/watershed_segmentation.py
cellmap_analyze/util/__init__.py
cellmap_analyze/util/block_util.py
cellmap_analyze/util/dask_util.py
cellmap_analyze/util/image_data_interface.py
cellmap_analyze/util/information_holders.py
cellmap_analyze/util/io_util.py
cellmap_analyze/util/mask_util.py
cellmap_analyze/util/measure_util.py
cellmap_analyze/util/mixins.py
cellmap_analyze/util/neuroglancer_util.py
cellmap_analyze/util/skeleton_util.py
cellmap_analyze/util/zarr_util.py
cli/__init__.py
cli/cli.py
cellmap_analyze-0.1.5.dist-info/METADATA
cellmap_analyze-0.1.5.dist-info/WHEEL
cellmap_analyze-0.1.5.dist-info/entry_points.txt
cellmap_analyze-0.1.5.dist-info/top_level.txt
cellmap_analyze-0.1.5.dist-info/RECORD
cellmap_analyze-0.1.5.dist-info/licenses/LICENSE
