Metadata-Version: 2.4
Name: cellmap-analyze
Version: 0.1.5
Summary: Code to perform analysis on segmentations like those produced by CellMap
Author-email: David Ackerman <ackermand@janelia.hhmi.org>
Maintainer-email: David Ackerman <ackermand@janelia.hhmi.org>
Requires-Python: <3.13,>=3.10
License-File: LICENSE
Requires-Dist: bokeh>=3.1.0
Requires-Dist: fastremap==1.15.2
Requires-Dist: funlib.geometry
Requires-Dist: funlib.persistence==0.3.0
Requires-Dist: numpy
Requires-Dist: pandas
Requires-Dist: connected-components-3d
Requires-Dist: dask[distributed]==2025.5.1
Requires-Dist: dask-jobqueue==0.9.0
Requires-Dist: fastmorph
Requires-Dist: pybind11-rdp==0.1.5
Requires-Dist: scipy
Requires-Dist: scikit-image
Requires-Dist: tensorstore
Requires-Dist: tqdm
Requires-Dist: zarr==2.18.5
Requires-Dist: numcodecs==0.13.0
Requires-Dist: mwatershed==0.5.2
Requires-Dist: pyarrow
Requires-Dist: neuroglancer
Provides-Extra: dev
Requires-Dist: pytest; extra == "dev"
Requires-Dist: pytest-cov; extra == "dev"
Requires-Dist: coverage; extra == "dev"
Requires-Dist: build; extra == "dev"
Dynamic: license-file
